pyarrow_unity/__init__.py
pyarrow_unity/model.py
pyarrow_unity-0.1.0.dist-info/METADATA
pyarrow_unity-0.1.0.dist-info/WHEEL
pyarrow_unity-0.1.0.dist-info/licenses/LICENSE
pyarrow_unity-0.1.0.dist-info/RECORD
