Metadata-Version: 2.3
Name: pyarrow-unity
Version: 0.1.0
Summary: Convert Pyarrow schema to Unity Catalog schema
Author-email: Frank Mbonu <frank.mbonu@xebia.com>, Frank Mbonu <daniel.tom@xebia.com>
License-File: LICENSE
Requires-Python: >=3.10
Requires-Dist: pyarrow>=17.0.0
Requires-Dist: unitycatalog>=0.1.1
